<?xml version="1.0" encoding="ISO-8859-1"?>
<monster name="Mega Gengar" nameDescription="a mega gengar" race="ghost" race2="poison" experience="250" speed="210" manacost="0">
	<level min="90" max="90"/>
	<health now="600" max="600" />
	<look type="3516" head="113" body="57" legs="95" feet="113" corpse="26955" />
	<targetchange interval="5000" chance="0" />
	<flags>
		<flag summonable="1" />
		<flag attackable="1" />
		<flag hostile="1" />
		<flag passive="0" />
		<flag illusionable="1" />
		<flag convinceable="1" />
		<flag pushable="1" />
		<flag canpushitems="0" />
		<flag canpushcreatures="0" />
		<flag targetdistance="1" />
		<flag staticattack="97" />
		<flag runonhealth="0" />
		<flag dexentry="94" />
		<flag portraitid="27210" />
		<flag hasshiny="1" />
		<flag hasmega="0" />
		<flag flyable="3517" />
		<flag rideable="0" />
		<flag surfable="0" />
		<flag canteleport="0" />
		<flag catchchance="0" />
		<flag moveMagicAttackBase="204" />
		<flag moveMagicDefenseBase="114" />
	</flags>
	<script>
        	<event name="MonsterHealthChange"/>
        	<event name="CorpseLevel"/>
        	<event name="CorpseLoot"/>

	</script>
	<moves>
		<move name="shadow punch" interval="2500" isTarget="1" range="3" level="1"/>
		<move name="sucker punch" interval="3500" isTarget="1" range="3" level="1"/>
		<move name="shadow ball" interval="5500" level="1"/>
		<move name="night shade" interval="6500" level="1"/>
		<move name="shadow claw" interval="7500" level="1"/>
		<move name="phantom force" interval="20000" level="1"/>
		<move name="hex" interval="15000" level="1"/>
		<move name="astonish" interval="12500" level="1"/>
		<move name="perish song" interval="17500" level="1"/>
		<move name="dream eater" interval="10000" level="1"/>
		<move name="curse" interval="15000" level="1"/>
		
	</moves>
	<evolutions>

	</evolutions>
	<attacks>
		<attack name="melee" interval="2000" min="-78" max="-78" />
		<attack name="shadow punch" interval="2500" chance="66" target="1"/>
		<attack name="sucker punch" interval="3500" chance="66" target="1"/>
		<attack name="shadow ball" interval="5500" chance="66" target="1"/>
		<attack name="night shade" interval="6500" chance="66" target="1"/>
		<attack name="shadow claw" interval="7500" chance="66" target="1"/>
		<attack name="phantom force" interval="20000" chance="66" target="1"/>
		<attack name="hex" interval="15000" chance="66" target="1"/>
		<attack name="astonish" interval="12500" chance="66" target="1"/>
		<attack name="perish song" interval="17500" chance="66" target="1"/>
		<attack name="dream eater" interval="10000" chance="66" target="1"/>
		<attack name="curse" interval="15000" chance="66" target="1"/>
		
		<attack name="hypnosis" interval="10000" chance="66"/>

	</attacks>
	<defenses armor="0" defense="96" >
		<defense name="hypnosis" interval="10000" chance="66"/>

	</defenses>
	<elements>
	</elements>
	<immunities>

	</immunities>
	<voices interval="5000" chance="10">
		<voice sentence="GENGAR!" />
	</voices>
	<loot>
		<item name="gengarite" countmax="1" chance="100"/>
		<item name="platinum coin" countmax="5" chance="100000"/>
		<item name="vale token" countmax="1" chance="15000"/>
	</loot>
</monster>
